alb_response/__init__.py
alb_response/responder.py
alb_response-0.1.2.dist-info/LICENSE.md
alb_response-0.1.2.dist-info/METADATA
alb_response-0.1.2.dist-info/WHEEL
alb_response-0.1.2.dist-info/top_level.txt
alb_response-0.1.2.dist-info/RECORD
