Metadata-Version: 2.1
Name: alb-response
Version: 0.1.2
Summary: UNKNOWN
Home-page: UNKNOWN
Author: djfurman
Author-email: djfurman@gmail.com
License: BSD-3-Clause
Platform: UNKNOWN
